notion_mcp/__init__.py
notion_mcp/__main__.py
notion_mcp/client.py
notion_mcp/server.py
notion_mcp/models/__init__.py
notion_mcp/models/notion.py
iflow_mcp_notion_mcp-0.2.0.dist-info/METADATA
iflow_mcp_notion_mcp-0.2.0.dist-info/WHEEL
iflow_mcp_notion_mcp-0.2.0.dist-info/entry_points.txt
iflow_mcp_notion_mcp-0.2.0.dist-info/licenses/LICENSE
iflow_mcp_notion_mcp-0.2.0.dist-info/RECORD
