Metadata-Version: 2.4
Name: iflow-mcp_notion-mcp
Version: 0.2.0
Summary: MCP server for Notion integration
Author-email: Chase Cabanillas <chase.cabanillas@gmail.com>
License-File: LICENSE
Requires-Python: >=3.10
Requires-Dist: httpx>=0.27.0
Requires-Dist: mcp>=0.2.0
Requires-Dist: pydantic>=2.5.0
Requires-Dist: python-dotenv>=1.0.0
Requires-Dist: rich>=13.7.0
